stm32cubeprog/__init__.py
stm32cubeprog/api.py
python_stm32cubeprog-0.1.1.dist-info/METADATA
python_stm32cubeprog-0.1.1.dist-info/WHEEL
python_stm32cubeprog-0.1.1.dist-info/licenses/LICENSE
python_stm32cubeprog-0.1.1.dist-info/RECORD
