Metadata-Version: 2.4
Name: python-stm32cubeprog
Version: 0.1.1
Summary: Python API for STM32CubeProgrammer
Project-URL: Homepage, https://github.com/wervin/python-stm32cubeprog
Project-URL: Bug Tracker, https://github.com/wervin/python-stm32cubeprog/issues
Author-email: Vincent Werner <vincent.werner@outlook.fr>
License-Expression: MIT
License-File: LICENSE
Classifier: License :: OSI Approved :: MIT License
Classifier: Operating System :: OS Independent
Classifier: Programming Language :: Python :: 3
Requires-Python: >=3.11
Requires-Dist: numpy
